jwskate/__init__.py
jwskate/_version.py
jwskate/enums.py
jwskate/py.typed
jwskate/token.py
jwskate/jwa/__init__.py
jwskate/jwa/base.py
jwskate/jwa/ec.py
jwskate/jwa/okp.py
jwskate/jwa/encryption/__init__.py
jwskate/jwa/encryption/aescbchmac.py
jwskate/jwa/encryption/aesgcm.py
jwskate/jwa/key_mgmt/__init__.py
jwskate/jwa/key_mgmt/aesgcmkw.py
jwskate/jwa/key_mgmt/aeskw.py
jwskate/jwa/key_mgmt/dir.py
jwskate/jwa/key_mgmt/ecdh.py
jwskate/jwa/key_mgmt/pbes2.py
jwskate/jwa/key_mgmt/rsa.py
jwskate/jwa/signature/__init__.py
jwskate/jwa/signature/ec.py
jwskate/jwa/signature/eddsa.py
jwskate/jwa/signature/hmac.py
jwskate/jwa/signature/rsa.py
jwskate/jwe/__init__.py
jwskate/jwe/compact.py
jwskate/jwk/__init__.py
jwskate/jwk/alg.py
jwskate/jwk/base.py
jwskate/jwk/ec.py
jwskate/jwk/jwks.py
jwskate/jwk/oct.py
jwskate/jwk/okp.py
jwskate/jwk/rsa.py
jwskate/jws/__init__.py
jwskate/jws/compact.py
jwskate/jws/json.py
jwskate/jws/signature.py
jwskate/jwt/__init__.py
jwskate/jwt/base.py
jwskate/jwt/signed.py
jwskate/jwt/signer.py
jwskate/jwt/verifier.py
jwskate-0.11.0.dist-info/METADATA
jwskate-0.11.0.dist-info/WHEEL
jwskate-0.11.0.dist-info/licenses/AUTHORS.md
jwskate-0.11.0.dist-info/licenses/LICENSE
jwskate-0.11.0.dist-info/RECORD
