Metadata-Version: 2.1
Name: jwskate
Version: 0.11.0
Summary: A Pythonic implementation of the JOSE / JSON Web Crypto related RFCs (JWS, JWK, JWA, JWT, JWE)
Project-URL: homepage, https://github.com/guillp/jwskate
Project-URL: documentation, https://guillp.github.io/jwskate/
Project-URL: pypi, https://pypi.org/project/jwskate/
Author-email: Guillaume Pujol <guill.p.linux@gmail.com>
License-Expression: MIT
License-File: AUTHORS.md
License-File: LICENSE
Classifier: Development Status :: 4 - Beta
Classifier: Intended Audience :: Developers
Classifier: License :: OSI Approved :: MIT License
Classifier: Programming Language :: Python :: 3
Classifier: Programming Language :: Python :: 3.8
Classifier: Programming Language :: Python :: 3.9
Classifier: Programming Language :: Python :: 3.10
Classifier: Programming Language :: Python :: 3.11
Classifier: Programming Language :: Python :: 3.12
Classifier: Topic :: Security
Requires-Python: >=3.8
Requires-Dist: binapy>=0.8
Requires-Dist: cryptography>=3.4
Requires-Dist: typing-extensions>=4.3
